prepare.cpython-310-x86_64-linux-gnu.so
prepare.cpython-311-x86_64-linux-gnu.so
prepare.cpython-312-x86_64-linux-gnu.so
prepare.cpython-313-x86_64-linux-gnu.so
prepare.pxd
prepare.pyx
read.pxd
write.pxd
cerializer/__init__.py
cerializer/cerializer_handler.py
cerializer/compiler.py
cerializer/constants.py
cerializer/py.typed
cerializer/schema_handler.py
cerializer/schema_parser.py
cerializer/utils.py
cerializer/templates/array_deserialization.jinja2
cerializer/templates/array_serialization.jinja2
cerializer/templates/map_deserialization.jinja2
cerializer/templates/map_serialization.jinja2
cerializer/templates/meta_template.jinja2
cerializer/templates/template.jinja2
cerializer/templates/union_deserialization.jinja2
cerializer/templates/union_serialization.jinja2
cerializer/tests/__init__.py
cerializer/tests/benchmark.py
cerializer/tests/test_cerializer.py
cerializer/tests/schemata/cerializer.array_schema:1/example.yaml
cerializer/tests/schemata/cerializer.array_schema:1/schema.yaml
cerializer/tests/schemata/cerializer.array_schema:2/example.yaml
cerializer/tests/schemata/cerializer.array_schema:2/schema.yaml
cerializer/tests/schemata/cerializer.array_schema:3/example.yaml
cerializer/tests/schemata/cerializer.array_schema:3/schema.yaml
cerializer/tests/schemata/cerializer.array_schema:4/example.yaml
cerializer/tests/schemata/cerializer.array_schema:4/schema.yaml
cerializer/tests/schemata/cerializer.bytes_decimal_schema:1/example.yaml
cerializer/tests/schemata/cerializer.bytes_decimal_schema:1/schema.yaml
cerializer/tests/schemata/cerializer.default_schema:1/example.yaml
cerializer/tests/schemata/cerializer.default_schema:1/schema.yaml
cerializer/tests/schemata/cerializer.default_schema:2/example.yaml
cerializer/tests/schemata/cerializer.default_schema:2/schema.yaml
cerializer/tests/schemata/cerializer.default_schema:3/example.yaml
cerializer/tests/schemata/cerializer.default_schema:3/schema.yaml
cerializer-1.5.1.dist-info/METADATA
cerializer-1.5.1.dist-info/WHEEL
cerializer-1.5.1.dist-info/RECORD
