Metadata-Version: 2.1
Name: cerializer
Version: 1.5.1
Summary: Even faster alternative to FastAvro
Home-page: https://gitlab.com/quantlane/libs/cerializer
Keywords: packaging,poetry
Author: matejmicek
Author-email: matej.micek@quantlane.com
Maintainer: Quantlane
Maintainer-email: code@quantlane.com
Requires-Python: >=3.10,<4.0
Classifier: Intended Audience :: Developers
Classifier: Operating System :: POSIX :: Linux
Classifier: Programming Language :: Cython
Classifier: Programming Language :: Python
Classifier: Programming Language :: Python :: 3
Classifier: Programming Language :: Python :: 3.10
Classifier: Programming Language :: Python :: 3.11
Classifier: Programming Language :: Python :: 3.12
Classifier: Programming Language :: Python :: Implementation :: CPython
Classifier: Topic :: Scientific/Engineering :: Information Analysis
Classifier: Topic :: Software Development :: Libraries
Classifier: Topic :: Software Development :: Libraries :: Python Modules
Provides-Extra: quantlane
Requires-Dist: cython (>=0.29.33,<3.1.0)
Requires-Dist: jinja2 (>=3.1.2,<4.0.0)
Requires-Dist: pyyaml (>=6.0.1,<7.0.0)
Requires-Dist: ql-qutils (>=10.1.2,<11.0.0) ; extra == "quantlane"
Requires-Dist: setuptools (>=46.0.0)
Project-URL: Repository, https://gitlab.com/quantlane/libs/cerializer
